lab02/task2/sword_fsm.sv
module sword_FSM(input logic clk,
                 input logic reset,
                 input logic[2:0] place,
                 output reg sword);
  reg state;

  assign sword = state;

  always @(posedge clk, posedge reset)
      if (reset)
        state <= 1'b0;
      else
        if (place == 3'b011)
          state <= 1'b1;

endmodule

lab02/task2/place_fsm.sv
module place_FSM(input logic clk,
                 input logic reset,
                 input logic[1:0] dir,
                 input logic sword,
                 output reg[2:0] place);

  reg[2:0] state;

  localparam[2:0]
    cave  = 3'b000,
    tunnel = 3'b001,
    river = 3'b010,
    cache = 3'b011,
    dragon = 3'b100,
    win = 3'b101,
    die = 3'b110,
    not_princess = 3'b111;

  localparam[1:0]
    l = 2'b00,
    r = 2'b01,
    u = 2'b10,
    d = 2'b11;

  assign place = state;

  always @(posedge clk, posedge reset)
    begin
      if (reset)
        state <= cave;
      else
        begin
          case (state)
            cave:
              state <= tunnel;
            tunnel:
              case (dir)
                l:
                  state <= cave;
                d:
                  state <= river;
                r:
                  state <= not_princess;
              endcase
            river:
              case (dir)
                l:
                  state <= cache;
                u:
                  state <= tunnel;
                r:
                  state <= dragon;
              endcase
            cache:
              state <= river;
            not_princess:
              state <= dragon;
            dragon:
              if (sword)
                state <= win;
              else 
                state <= die;
          endcase
        end
    end

endmodule

lab02/task2/game.sv
`include "place_fsm.sv"
`include "sword_fsm.sv"

module game(input logic clk,
            input logic reset,
            input logic[1:0] dir,
            output logic[1:0] result);
  localparam[1:0]
    in_process = 2'b00,
    win = 2'b01,
    die = 2'b10;

  localparam[2:0]
    cave  = 3'b000,
    tunnel = 3'b001,
    river = 3'b010,
    cache = 3'b011,
    dragon = 3'b100,
    victorious_vault = 3'b101,
    cemetery = 3'b110;

  logic sword;
  logic[2:0] place;

  place_FSM pl_fsm(clk, reset, dir, sword, place);
  sword_FSM sw_fsm(clk, reset, place, sword);

  always @(place)
    begin
      case (place)
        victorious_vault: 
          result <= win;
        cemetery:
          result <= die;
        default:
          result <= in_process;
      endcase
    end

endmodule

lab02/task2/testbench.sv
`include "game.sv"

module testbench(); 
  logic        clk, reset;
  logic [1:0]  dir, result;
  logic [1:0]  expected;
  logic [31:0] vectornum, errors;
  logic [3:0]  testvectors[10000:0];

// инстанцировать тестируемое устройство 
game dut(clk, reset, dir, result); 

// generate clock 
always 
  begin
    clk=1; #5; clk=0; #5; 
  end 

// на старте теста, загрузите вектора и запустите сброс
initial 
  begin
    $dumpfile("testbench.vcd");
    $dumpvars(0, testbench);

    $readmemb("testvectors.tv", testvectors); 
    vectornum = 0; errors = 0; reset = 1; #18; reset = 0; 
  end 

// применение тестовых векторов по нарастающему фронту тактового сигнала
always @(posedge clk) 
  begin
    {dir, expected} = testvectors[vectornum]; 
  end 

// проверка результатов по спадающему фронту сигнала clk
always @(negedge clk) 
  if (~reset) begin    // skip during reset
    if (result !== expected) begin // check result 
      $display("Error: inputs = %b", dir);
      $display(" outputs = %b (%b expected)", 
        result, expected); 
      errors = errors + 1; 
    end
    if (result !== 2'b00)
    begin
      reset = 1; #22; reset = 0;
    end
    vectornum = vectornum + 1;
    if (testvectors[vectornum] === 4'bx) begin 
      $display("%d tests completed with %d errors", vectornum, errors); 
      $finish;
    end 
  end 
endmodule

lab02/task2/testbench.vcd
$date
	Tue Apr 12 17:56:39 2022
$end
$version
	Icarus Verilog
$end
$timescale
	1s
$end
$scope module testbench $end
$var wire 2 ! result [1:0] $end
$var reg 1 " clk $end
$var reg 2 # dir [1:0] $end
$var reg 32 $ errors [31:0] $end
$var reg 2 % expected [1:0] $end
$var reg 1 & reset $end
$var reg 32 ' vectornum [31:0] $end
$scope module dut $end
$var wire 1 " clk $end
$var wire 2 ( dir [1:0] $end
$var wire 1 & reset $end
$var wire 1 ) sword $end
$var wire 3 * place [2:0] $end
$var reg 2 + result [1:0] $end
$scope module pl_fsm $end
$var wire 1 " clk $end
$var wire 2 , dir [1:0] $end
$var wire 3 - place [2:0] $end
$var wire 1 & reset $end
$var wire 1 ) sword $end
$var reg 3 . state [2:0] $end
$upscope $end
$scope module sw_fsm $end
$var wire 1 " clk $end
$var wire 3 / place [2:0] $end
$var wire 1 & reset $end
$var wire 1 ) sword $end
$var reg 1 0 state $end
$upscope $end
$upscope $end
$upscope $end
$enddefinitions $end
#0
$dumpvars
00
b0 /
b0 .
b0 -
bx ,
b0 +
b0 *
0)
bx (
b0 '
1&
bx %
b0 $
bx #
1"
b0 !
$end
#5
0"
#10
b1 #
b1 (
b1 ,
b0 %
1"
#15
0"
#18
0&
#20
b1 *
b1 -
b1 /
b1 .
1"
#25
b1 '
0"
#30
b10 *
b10 -
b10 /
b10 .
b11 #
b11 (
b11 ,
1"
#35
b10 '
0"
#40
b11 *
b11 -
b11 /
b11 .
b0 #
b0 (
b0 ,
1"
#45
b11 '
0"
#50
1)
10
b10 *
b10 -
b10 /
b10 .
b1 #
b1 (
b1 ,
1"
#55
b100 '
0"
#60
b1 *
b1 -
b1 /
b1 .
b10 #
b10 (
b10 ,
1"
#65
b101 '
0"
#70
b10 *
b10 -
b10 /
b10 .
b11 #
b11 (
b11 ,
1"
#75
b110 '
0"
#80
b100 *
b100 -
b100 /
b100 .
b1 #
b1 (
b1 ,
1"
#85
b111 '
0"
#90
b1 !
b1 +
b101 *
b101 -
b101 /
b101 .
b0 #
b0 (
b0 ,
b1 %
1"
#95
b0 !
b0 +
b0 *
b0 -
b0 /
b0 .
0)
00
1&
0"
#100
1"
#105
0"
#110
1"
#115
0"
#117
b1000 '
0&
#120
b1 *
b1 -
b1 /
b1 .
b1 #
b1 (
b1 ,
b0 %
1"
#125
b1001 '
0"
#130
b10 *
b10 -
b10 /
b10 .
b11 #
b11 (
b11 ,
1"
#135
b1010 '
0"
#140
b100 *
b100 -
b100 /
b100 .
b1 #
b1 (
b1 ,
1"
#145
b1011 '
0"
#150
b10 !
b10 +
b110 *
b110 -
b110 /
b110 .
b10 %
1"
#155
b0 !
b0 +
b0 *
b0 -
b0 /
b0 .
1&
0"
#160
1"
#165
0"
#170
1"
#175
0"
#177
b1100 '
0&
